contrib_colormaps/__init__.py
contrib_colormaps/_version.py
contrib_colormaps/core.py
contrib_colormaps/plotting.py
contrib_colormaps/colormaps/sample.csv
contrib_colormaps/tests/__init__.py
contrib_colormaps/tests/test_bokeh.py
contrib_colormaps/tests/test_colormaps.py
contrib_colormaps/tests/test_matplotlib.py
contrib_colormaps-0.0.1.dist-info/LICENSE.txt
contrib_colormaps-0.0.1.dist-info/METADATA
contrib_colormaps-0.0.1.dist-info/WHEEL
contrib_colormaps-0.0.1.dist-info/top_level.txt
contrib_colormaps-0.0.1.dist-info/RECORD
