Metadata-Version: 2.1
Name: contrib-colormaps
Version: 0.0.1
Summary: Contributed colormaps
Home-page: https://contrib_colormaps.pyviz.org
Author: PyViz Developers
Author-email: jsignell@gmail.com
Maintainer: Julia Signell
Maintainer-email: jsignell@gmail.com
License: CC-BY License
Project-URL: Bug Tracker, http://github.com/pyviz/contrib_colormaps/issues
Project-URL: Documentation, https://contrib_colormaps.pyviz.org
Project-URL: Source Code, http://github.com/pyviz/contrib_colormaps
Platform: UNKNOWN
Classifier: License :: Other/Proprietary License
Classifier: Operating System :: OS Independent
Classifier: Programming Language :: Python
Classifier: Programming Language :: Python :: 2.7
Classifier: Programming Language :: Python :: 3.6
Classifier: Programming Language :: Python :: 3.7
Classifier: Development Status :: 5 - Production/Stable
Requires-Python: >=2.7
Provides-Extra: all
Requires-Dist: bokeh ; extra == 'all'
Requires-Dist: flake8 ; extra == 'all'
Requires-Dist: holoviews ; extra == 'all'
Requires-Dist: matplotlib ; extra == 'all'
Requires-Dist: nbsite (>=0.6.1) ; extra == 'all'
Requires-Dist: nbsmoke (>=0.2.6) ; extra == 'all'
Requires-Dist: numpy ; extra == 'all'
Requires-Dist: pytest (>=2.8.5) ; extra == 'all'
Requires-Dist: pytest-mpl ; extra == 'all'
Requires-Dist: selenium ; extra == 'all'
Requires-Dist: setuptools ; extra == 'all'
Requires-Dist: tornado (<6) ; extra == 'all'
Requires-Dist: wheel ; extra == 'all'
Provides-Extra: build
Requires-Dist: setuptools ; extra == 'build'
Requires-Dist: wheel ; extra == 'build'
Provides-Extra: doc
Requires-Dist: numpy ; extra == 'doc'
Requires-Dist: holoviews ; extra == 'doc'
Requires-Dist: matplotlib ; extra == 'doc'
Requires-Dist: bokeh ; extra == 'doc'
Requires-Dist: nbsite (>=0.6.1) ; extra == 'doc'
Requires-Dist: tornado (<6) ; extra == 'doc'
Requires-Dist: selenium ; extra == 'doc'
Provides-Extra: examples
Requires-Dist: numpy ; extra == 'examples'
Requires-Dist: holoviews ; extra == 'examples'
Requires-Dist: matplotlib ; extra == 'examples'
Requires-Dist: bokeh ; extra == 'examples'
Provides-Extra: tests
Requires-Dist: flake8 ; extra == 'tests'
Requires-Dist: nbsmoke (>=0.2.6) ; extra == 'tests'
Requires-Dist: pytest (>=2.8.5) ; extra == 'tests'
Provides-Extra: tests_extra
Requires-Dist: flake8 ; extra == 'tests_extra'
Requires-Dist: nbsmoke (>=0.2.6) ; extra == 'tests_extra'
Requires-Dist: pytest (>=2.8.5) ; extra == 'tests_extra'
Requires-Dist: pytest-mpl ; extra == 'tests_extra'
